autoregressive_language_model_generate.py
autoregressive_language_model_generate-0.1.0a0.dist-info/licenses/LICENSE
autoregressive_language_model_generate-0.1.0a0.dist-info/METADATA
autoregressive_language_model_generate-0.1.0a0.dist-info/WHEEL
autoregressive_language_model_generate-0.1.0a0.dist-info/top_level.txt
autoregressive_language_model_generate-0.1.0a0.dist-info/RECORD
