Metadata-Version: 2.4
Name: autoregressive-language-model-generate
Version: 0.1.0a0
Summary: A generator-based, stateless autoregressive inference loop for language models compatible with HuggingFace's Transformers API.
Author-email: Jifeng Wu <jifengwu2k@gmail.com>
License-Expression: MIT
Project-URL: Homepage, https://github.com/jifengwu2k/autoregressive-language-model-generate
Project-URL: Bug Tracker, https://github.com/jifengwu2k/autoregressive-language-model-generate/issues
Classifier: Programming Language :: Python :: 2
Classifier: Programming Language :: Python :: 3
Classifier: Operating System :: OS Independent
Requires-Python: >=2
License-File: LICENSE
Requires-Dist: torch
Requires-Dist: typing; python_version < "3.5"
Dynamic: license-file
